{
  "id": "c57b0904-8a46-4ba6-b83e-ae35e8e09c3d",
  "prevId": "00000000-0000-0000-0000-000000000000",
  "version": "7",
  "dialect": "postgresql",
  "tables": {
    "public.category_tree": {
      "name": "category_tree",
      "schema": "",
      "columns": {
        "parent_category_id": {
          "name": "parent_category_id",
          "type": "integer",
          "primaryKey": false,
          "notNull": true
        },
        "child_category_id": {
          "name": "child_category_id",
          "type": "integer",
          "primaryKey": false,
          "notNull": true
        }
      },
      "indexes": {},
      "foreignKeys": {
        "category_tree_parent_category_id_categories_id_fk": {
          "name": "category_tree_parent_category_id_categories_id_fk",
          "tableFrom": "category_tree",
          "tableTo": "categories",
          "columnsFrom": [
            "parent_category_id"
          ],
          "columnsTo": [
            "id"
          ],
          "onDelete": "cascade",
          "onUpdate": "no action"
        },
        "category_tree_child_category_id_categories_id_fk": {
          "name": "category_tree_child_category_id_categories_id_fk",
          "tableFrom": "category_tree",
          "tableTo": "categories",
          "columnsFrom": [
            "child_category_id"
          ],
          "columnsTo": [
            "id"
          ],
          "onDelete": "no action",
          "onUpdate": "no action"
        }
      },
      "compositePrimaryKeys": {
        "category_tree_pk": {
          "name": "category_tree_pk",
          "columns": [
            "child_category_id",
            "parent_category_id"
          ]
        }
      },
      "uniqueConstraints": {},
      "policies": {},
      "checkConstraints": {},
      "isRLSEnabled": false
    },
    "public.categories": {
      "name": "categories",
      "schema": "",
      "columns": {
        "id": {
          "name": "id",
          "type": "serial",
          "primaryKey": true,
          "notNull": true
        },
        "label": {
          "name": "label",
          "type": "varchar(50)",
          "primaryKey": false,
          "notNull": true
        },
        "description": {
          "name": "description",
          "type": "varchar(150)",
          "primaryKey": false,
          "notNull": false
        }
      },
      "indexes": {},
      "foreignKeys": {},
      "compositePrimaryKeys": {},
      "uniqueConstraints": {
        "categories_id_unique": {
          "name": "categories_id_unique",
          "nullsNotDistinct": false,
          "columns": [
            "id"
          ]
        },
        "categories_label_unique": {
          "name": "categories_label_unique",
          "nullsNotDistinct": false,
          "columns": [
            "label"
          ]
        }
      },
      "policies": {},
      "checkConstraints": {},
      "isRLSEnabled": false
    },
    "public.socials": {
      "name": "socials",
      "schema": "",
      "columns": {
        "id": {
          "name": "id",
          "type": "serial",
          "primaryKey": true,
          "notNull": true
        },
        "user_id": {
          "name": "user_id",
          "type": "uuid",
          "primaryKey": false,
          "notNull": true
        },
        "platform": {
          "name": "platform",
          "type": "varchar(50)",
          "primaryKey": false,
          "notNull": false
        },
        "handle": {
          "name": "handle",
          "type": "varchar(24)",
          "primaryKey": false,
          "notNull": false
        }
      },
      "indexes": {},
      "foreignKeys": {
        "socials_user_id_users_id_fk": {
          "name": "socials_user_id_users_id_fk",
          "tableFrom": "socials",
          "tableTo": "users",
          "columnsFrom": [
            "user_id"
          ],
          "columnsTo": [
            "id"
          ],
          "onDelete": "cascade",
          "onUpdate": "no action"
        }
      },
      "compositePrimaryKeys": {},
      "uniqueConstraints": {},
      "policies": {},
      "checkConstraints": {},
      "isRLSEnabled": false
    },
    "public.userRoles": {
      "name": "userRoles",
      "schema": "",
      "columns": {
        "user_id": {
          "name": "user_id",
          "type": "uuid",
          "primaryKey": false,
          "notNull": true
        },
        "role_id": {
          "name": "role_id",
          "type": "integer",
          "primaryKey": false,
          "notNull": true
        },
        "assigned_at": {
          "name": "assigned_at",
          "type": "timestamp",
          "primaryKey": false,
          "notNull": true,
          "default": "now()"
        },
        "expires_at": {
          "name": "expires_at",
          "type": "timestamp",
          "primaryKey": false,
          "notNull": true,
          "default": "now()"
        },
        "updated_at": {
          "name": "updated_at",
          "type": "timestamp",
          "primaryKey": false,
          "notNull": true,
          "default": "now()"
        }
      },
      "indexes": {},
      "foreignKeys": {
        "userRoles_user_id_users_id_fk": {
          "name": "userRoles_user_id_users_id_fk",
          "tableFrom": "userRoles",
          "tableTo": "users",
          "columnsFrom": [
            "user_id"
          ],
          "columnsTo": [
            "id"
          ],
          "onDelete": "cascade",
          "onUpdate": "no action"
        },
        "userRoles_role_id_roles_id_fk": {
          "name": "userRoles_role_id_roles_id_fk",
          "tableFrom": "userRoles",
          "tableTo": "roles",
          "columnsFrom": [
            "role_id"
          ],
          "columnsTo": [
            "id"
          ],
          "onDelete": "cascade",
          "onUpdate": "no action"
        }
      },
      "compositePrimaryKeys": {
        "pk_userRoles": {
          "name": "pk_userRoles",
          "columns": [
            "role_id",
            "user_id"
          ]
        }
      },
      "uniqueConstraints": {},
      "policies": {},
      "checkConstraints": {},
      "isRLSEnabled": false
    },
    "public.users": {
      "name": "users",
      "schema": "",
      "columns": {
        "id": {
          "name": "id",
          "type": "uuid",
          "primaryKey": true,
          "notNull": true,
          "default": "gen_random_uuid()"
        },
        "name": {
          "name": "name",
          "type": "text",
          "primaryKey": false,
          "notNull": true
        },
        "email": {
          "name": "email",
          "type": "varchar(100)",
          "primaryKey": false,
          "notNull": true
        },
        "username": {
          "name": "username",
          "type": "varchar(24)",
          "primaryKey": false,
          "notNull": true
        },
        "created_at": {
          "name": "created_at",
          "type": "timestamp",
          "primaryKey": false,
          "notNull": true,
          "default": "now()"
        },
        "updated_at": {
          "name": "updated_at",
          "type": "timestamp",
          "primaryKey": false,
          "notNull": true,
          "default": "now()"
        }
      },
      "indexes": {},
      "foreignKeys": {},
      "compositePrimaryKeys": {},
      "uniqueConstraints": {
        "users_email_unique": {
          "name": "users_email_unique",
          "nullsNotDistinct": false,
          "columns": [
            "email"
          ]
        },
        "users_username_unique": {
          "name": "users_username_unique",
          "nullsNotDistinct": false,
          "columns": [
            "username"
          ]
        }
      },
      "policies": {},
      "checkConstraints": {},
      "isRLSEnabled": false
    },
    "public.post_authors": {
      "name": "post_authors",
      "schema": "",
      "columns": {
        "post_id": {
          "name": "post_id",
          "type": "integer",
          "primaryKey": false,
          "notNull": false
        },
        "user_id": {
          "name": "user_id",
          "type": "uuid",
          "primaryKey": false,
          "notNull": false
        }
      },
      "indexes": {},
      "foreignKeys": {
        "post_authors_post_id_posts_id_fk": {
          "name": "post_authors_post_id_posts_id_fk",
          "tableFrom": "post_authors",
          "tableTo": "posts",
          "columnsFrom": [
            "post_id"
          ],
          "columnsTo": [
            "id"
          ],
          "onDelete": "cascade",
          "onUpdate": "no action"
        },
        "post_authors_user_id_users_id_fk": {
          "name": "post_authors_user_id_users_id_fk",
          "tableFrom": "post_authors",
          "tableTo": "users",
          "columnsFrom": [
            "user_id"
          ],
          "columnsTo": [
            "id"
          ],
          "onDelete": "cascade",
          "onUpdate": "no action"
        }
      },
      "compositePrimaryKeys": {
        "post_author_pk": {
          "name": "post_author_pk",
          "columns": [
            "post_id",
            "user_id"
          ]
        }
      },
      "uniqueConstraints": {},
      "policies": {},
      "checkConstraints": {},
      "isRLSEnabled": false
    },
    "public.post_categories": {
      "name": "post_categories",
      "schema": "",
      "columns": {
        "post_id": {
          "name": "post_id",
          "type": "integer",
          "primaryKey": false,
          "notNull": true
        },
        "category_id": {
          "name": "category_id",
          "type": "integer",
          "primaryKey": false,
          "notNull": true
        }
      },
      "indexes": {},
      "foreignKeys": {
        "post_categories_post_id_posts_id_fk": {
          "name": "post_categories_post_id_posts_id_fk",
          "tableFrom": "post_categories",
          "tableTo": "posts",
          "columnsFrom": [
            "post_id"
          ],
          "columnsTo": [
            "id"
          ],
          "onDelete": "cascade",
          "onUpdate": "no action"
        },
        "post_categories_category_id_categories_id_fk": {
          "name": "post_categories_category_id_categories_id_fk",
          "tableFrom": "post_categories",
          "tableTo": "categories",
          "columnsFrom": [
            "category_id"
          ],
          "columnsTo": [
            "id"
          ],
          "onDelete": "cascade",
          "onUpdate": "no action"
        }
      },
      "compositePrimaryKeys": {
        "postCat_pk": {
          "name": "postCat_pk",
          "columns": [
            "post_id",
            "category_id"
          ]
        }
      },
      "uniqueConstraints": {},
      "policies": {},
      "checkConstraints": {},
      "isRLSEnabled": false
    },
    "public.post_tags": {
      "name": "post_tags",
      "schema": "",
      "columns": {
        "post_id": {
          "name": "post_id",
          "type": "integer",
          "primaryKey": false,
          "notNull": true
        },
        "tag_id": {
          "name": "tag_id",
          "type": "integer",
          "primaryKey": false,
          "notNull": true
        }
      },
      "indexes": {},
      "foreignKeys": {
        "post_tags_post_id_posts_id_fk": {
          "name": "post_tags_post_id_posts_id_fk",
          "tableFrom": "post_tags",
          "tableTo": "posts",
          "columnsFrom": [
            "post_id"
          ],
          "columnsTo": [
            "id"
          ],
          "onDelete": "cascade",
          "onUpdate": "no action"
        },
        "post_tags_tag_id_tags_id_fk": {
          "name": "post_tags_tag_id_tags_id_fk",
          "tableFrom": "post_tags",
          "tableTo": "tags",
          "columnsFrom": [
            "tag_id"
          ],
          "columnsTo": [
            "id"
          ],
          "onDelete": "cascade",
          "onUpdate": "no action"
        }
      },
      "compositePrimaryKeys": {
        "postTags_pk": {
          "name": "postTags_pk",
          "columns": [
            "tag_id",
            "post_id"
          ]
        }
      },
      "uniqueConstraints": {},
      "policies": {},
      "checkConstraints": {},
      "isRLSEnabled": false
    },
    "public.posts": {
      "name": "posts",
      "schema": "",
      "columns": {
        "id": {
          "name": "id",
          "type": "serial",
          "primaryKey": true,
          "notNull": true
        },
        "title": {
          "name": "title",
          "type": "varchar(100)",
          "primaryKey": false,
          "notNull": true
        },
        "body": {
          "name": "body",
          "type": "text",
          "primaryKey": false,
          "notNull": true
        },
        "featured_img": {
          "name": "featured_img",
          "type": "text",
          "primaryKey": false,
          "notNull": false
        },
        "created_at": {
          "name": "created_at",
          "type": "timestamp",
          "primaryKey": false,
          "notNull": true,
          "default": "now()"
        },
        "published_at": {
          "name": "published_at",
          "type": "timestamp",
          "primaryKey": false,
          "notNull": false,
          "default": "now()"
        },
        "updated_at": {
          "name": "updated_at",
          "type": "timestamp",
          "primaryKey": false,
          "notNull": true,
          "default": "now()"
        }
      },
      "indexes": {},
      "foreignKeys": {},
      "compositePrimaryKeys": {},
      "uniqueConstraints": {},
      "policies": {},
      "checkConstraints": {},
      "isRLSEnabled": false
    },
    "public.roles": {
      "name": "roles",
      "schema": "",
      "columns": {
        "id": {
          "name": "id",
          "type": "serial",
          "primaryKey": true,
          "notNull": true
        },
        "role_name": {
          "name": "role_name",
          "type": "varchar(50)",
          "primaryKey": false,
          "notNull": true
        },
        "description": {
          "name": "description",
          "type": "text",
          "primaryKey": false,
          "notNull": true
        },
        "role_code": {
          "name": "role_code",
          "type": "integer",
          "primaryKey": false,
          "notNull": true
        }
      },
      "indexes": {},
      "foreignKeys": {},
      "compositePrimaryKeys": {},
      "uniqueConstraints": {
        "roles_role_name_unique": {
          "name": "roles_role_name_unique",
          "nullsNotDistinct": false,
          "columns": [
            "role_name"
          ]
        },
        "roles_role_code_unique": {
          "name": "roles_role_code_unique",
          "nullsNotDistinct": false,
          "columns": [
            "role_code"
          ]
        }
      },
      "policies": {},
      "checkConstraints": {},
      "isRLSEnabled": false
    },
    "public.features": {
      "name": "features",
      "schema": "",
      "columns": {
        "id": {
          "name": "id",
          "type": "serial",
          "primaryKey": true,
          "notNull": true
        },
        "label": {
          "name": "label",
          "type": "varchar(100)",
          "primaryKey": false,
          "notNull": true
        },
        "description": {
          "name": "description",
          "type": "text",
          "primaryKey": false,
          "notNull": true
        }
      },
      "indexes": {},
      "foreignKeys": {},
      "compositePrimaryKeys": {},
      "uniqueConstraints": {
        "features_label_unique": {
          "name": "features_label_unique",
          "nullsNotDistinct": false,
          "columns": [
            "label"
          ]
        }
      },
      "policies": {},
      "checkConstraints": {},
      "isRLSEnabled": false
    },
    "public.subscription_features": {
      "name": "subscription_features",
      "schema": "",
      "columns": {
        "feature_id": {
          "name": "feature_id",
          "type": "integer",
          "primaryKey": false,
          "notNull": true
        },
        "subscription_id": {
          "name": "subscription_id",
          "type": "integer",
          "primaryKey": false,
          "notNull": true
        }
      },
      "indexes": {},
      "foreignKeys": {
        "subscription_features_feature_id_features_id_fk": {
          "name": "subscription_features_feature_id_features_id_fk",
          "tableFrom": "subscription_features",
          "tableTo": "features",
          "columnsFrom": [
            "feature_id"
          ],
          "columnsTo": [
            "id"
          ],
          "onDelete": "cascade",
          "onUpdate": "no action"
        },
        "subscription_features_subscription_id_subscriptions_id_fk": {
          "name": "subscription_features_subscription_id_subscriptions_id_fk",
          "tableFrom": "subscription_features",
          "tableTo": "subscriptions",
          "columnsFrom": [
            "subscription_id"
          ],
          "columnsTo": [
            "id"
          ],
          "onDelete": "cascade",
          "onUpdate": "no action"
        }
      },
      "compositePrimaryKeys": {
        "subFeat_pk": {
          "name": "subFeat_pk",
          "columns": [
            "feature_id",
            "subscription_id"
          ]
        }
      },
      "uniqueConstraints": {},
      "policies": {},
      "checkConstraints": {},
      "isRLSEnabled": false
    },
    "public.subscription_roles": {
      "name": "subscription_roles",
      "schema": "",
      "columns": {
        "subscription_id": {
          "name": "subscription_id",
          "type": "integer",
          "primaryKey": false,
          "notNull": true
        },
        "role_id": {
          "name": "role_id",
          "type": "integer",
          "primaryKey": false,
          "notNull": true
        }
      },
      "indexes": {},
      "foreignKeys": {
        "subscription_roles_subscription_id_subscriptions_id_fk": {
          "name": "subscription_roles_subscription_id_subscriptions_id_fk",
          "tableFrom": "subscription_roles",
          "tableTo": "subscriptions",
          "columnsFrom": [
            "subscription_id"
          ],
          "columnsTo": [
            "id"
          ],
          "onDelete": "cascade",
          "onUpdate": "no action"
        },
        "subscription_roles_role_id_roles_id_fk": {
          "name": "subscription_roles_role_id_roles_id_fk",
          "tableFrom": "subscription_roles",
          "tableTo": "roles",
          "columnsFrom": [
            "role_id"
          ],
          "columnsTo": [
            "id"
          ],
          "onDelete": "cascade",
          "onUpdate": "no action"
        }
      },
      "compositePrimaryKeys": {
        "subRole_pk": {
          "name": "subRole_pk",
          "columns": [
            "role_id",
            "subscription_id"
          ]
        }
      },
      "uniqueConstraints": {},
      "policies": {},
      "checkConstraints": {},
      "isRLSEnabled": false
    },
    "public.subscriptions": {
      "name": "subscriptions",
      "schema": "",
      "columns": {
        "id": {
          "name": "id",
          "type": "serial",
          "primaryKey": true,
          "notNull": true
        },
        "label": {
          "name": "label",
          "type": "varchar(100)",
          "primaryKey": false,
          "notNull": true
        },
        "description": {
          "name": "description",
          "type": "text",
          "primaryKey": false,
          "notNull": true
        },
        "price": {
          "name": "price",
          "type": "numeric(10, 2)",
          "primaryKey": false,
          "notNull": true,
          "default": "'0.00'"
        },
        "billing_period": {
          "name": "billing_period",
          "type": "varchar(50)",
          "primaryKey": false,
          "notNull": true
        }
      },
      "indexes": {},
      "foreignKeys": {},
      "compositePrimaryKeys": {},
      "uniqueConstraints": {
        "subscriptions_label_unique": {
          "name": "subscriptions_label_unique",
          "nullsNotDistinct": false,
          "columns": [
            "label"
          ]
        }
      },
      "policies": {},
      "checkConstraints": {},
      "isRLSEnabled": false
    },
    "public.tags": {
      "name": "tags",
      "schema": "",
      "columns": {
        "id": {
          "name": "id",
          "type": "serial",
          "primaryKey": true,
          "notNull": true
        },
        "label": {
          "name": "label",
          "type": "varchar(50)",
          "primaryKey": false,
          "notNull": true
        },
        "description": {
          "name": "description",
          "type": "varchar(150)",
          "primaryKey": false,
          "notNull": false
        }
      },
      "indexes": {},
      "foreignKeys": {},
      "compositePrimaryKeys": {},
      "uniqueConstraints": {
        "tags_label_unique": {
          "name": "tags_label_unique",
          "nullsNotDistinct": false,
          "columns": [
            "label"
          ]
        }
      },
      "policies": {},
      "checkConstraints": {},
      "isRLSEnabled": false
    }
  },
  "enums": {},
  "schemas": {},
  "sequences": {},
  "roles": {},
  "policies": {},
  "views": {},
  "_meta": {
    "columns": {},
    "schemas": {},
    "tables": {}
  }
}